aiorss/__init__.py
aiorss/client.py
aiorss/exceptions.py
aiorss/http_client.py
aiorss-0.1.0.dist-info/METADATA
aiorss-0.1.0.dist-info/RECORD
aiorss-0.1.0.dist-info/WHEEL
aiorss-0.1.0.dist-info/top_level.txt
