Metadata-Version: 2.1
Name: aiorss
Version: 0.1.0
Summary: Asyncio client for interacting with rss feeds
Home-page: https://github.com/mfdeux/aiorss
Author: Marc Ford
License: MIT
Platform: UNKNOWN
Classifier: License :: OSI Approved :: MIT License
Classifier: Programming Language :: Python :: 3.6
Classifier: Programming Language :: Python :: 3.7
Classifier: Operating System :: OS Independent
Requires-Dist: aiohttp
Requires-Dist: feedparser
